ebonite/__init__.py
ebonite/config.py
ebonite/build/__init__.py
ebonite/build/helpers.py
ebonite/build/builder/__init__.py
ebonite/build/builder/base.py
ebonite/build/provider/__init__.py
ebonite/build/provider/base.py
ebonite/build/provider/ml_model.py
ebonite/build/provider/ml_model_multi.py
ebonite/build/provider/pipeline.py
ebonite/build/provider/utils.py
ebonite/build/runner/__init__.py
ebonite/build/runner/base.py
ebonite/client/__init__.py
ebonite/client/autogen.py
ebonite/client/base.py
ebonite/client/expose.py
ebonite/client/helpers.py
ebonite/core/__init__.py
ebonite/core/errors.py
ebonite/core/analyzer/__init__.py
ebonite/core/analyzer/base.py
ebonite/core/analyzer/buildable.py
ebonite/core/analyzer/dataset.py
ebonite/core/analyzer/metric.py
ebonite/core/analyzer/model.py
ebonite/core/analyzer/requirement.py
ebonite/core/objects/__init__.py
ebonite/core/objects/artifacts.py
ebonite/core/objects/base.py
ebonite/core/objects/core.py
ebonite/core/objects/dataset_source.py
ebonite/core/objects/dataset_type.py
ebonite/core/objects/metric.py
ebonite/core/objects/requirements.py
ebonite/core/objects/typing.py
ebonite/core/objects/wrapper.py
ebonite/ext/__init__.py
ebonite/ext/ext_loader.py
ebonite/ext/aiohttp/__init__.py
ebonite/ext/aiohttp/server.py
ebonite/ext/catboost/__init__.py
ebonite/ext/catboost/model.py
ebonite/ext/docker/__init__.py
ebonite/ext/docker/base.py
ebonite/ext/docker/build_context.py
ebonite/ext/docker/builder.py
ebonite/ext/docker/dockerfile.j2
ebonite/ext/docker/helpers.py
ebonite/ext/docker/prebuild.py
ebonite/ext/docker/runner.py
ebonite/ext/docker/utils.py
ebonite/ext/flask/__init__.py
ebonite/ext/flask/client.py
ebonite/ext/flask/server.py
ebonite/ext/flask/build/app.py
ebonite/ext/flask/build/post_install.j2
ebonite/ext/flask/prebuild/Dockerfile.j2
ebonite/ext/flask/prebuild/app.py
ebonite/ext/flask/prebuild/flask-site-nginx.conf
ebonite/ext/flask/prebuild/nginx.conf
ebonite/ext/flask/prebuild/supervisord.conf
ebonite-0.7.0.dist-info/AUTHORS.rst
ebonite-0.7.0.dist-info/LICENSE
ebonite-0.7.0.dist-info/METADATA
ebonite-0.7.0.dist-info/WHEEL
ebonite-0.7.0.dist-info/entry_points.txt
ebonite-0.7.0.dist-info/top_level.txt
ebonite-0.7.0.dist-info/RECORD
