Metadata-Version: 2.1
Name: ebonite
Version: 0.7.0
Summary: Machine Learning Lifecycle Framework
Home-page: https://github.com/zyfra/ebonite
Author: Mikhail Sveshnikov
Author-email: mike0sv@gmail.com
License: Apache-2.0
Project-URL: Changelog, https://github.com/zyfra/ebonite/blob/master/CHANGELOG.rst
Project-URL: Issue Tracker, https://github.com/zyfra/ebonite/issues
Platform: UNKNOWN
Classifier: Development Status :: 5 - Production/Stable
Classifier: Intended Audience :: Developers
Classifier: License :: OSI Approved :: Apache Software License
Classifier: Operating System :: Unix
Classifier: Operating System :: POSIX
Classifier: Operating System :: Microsoft :: Windows
Classifier: Programming Language :: Python
Classifier: Programming Language :: Python :: 3.6
Classifier: Programming Language :: Python :: 3.7
Classifier: Topic :: Utilities
Requires-Python: >=3.6
Requires-Dist: docker (==4.2.0)
Requires-Dist: requests (==2.23.0)
Requires-Dist: dill (==0.3.1.1)
Requires-Dist: isort (==4.3.21)
Requires-Dist: pyjackson (==0.0.25)
Requires-Dist: everett (==1.0.2)
Requires-Dist: Jinja2 (==2.11.1)
Provides-Extra: testing
Requires-Dist: pandas (==1.0.3) ; extra == 'testing'
Requires-Dist: lxml (==4.5.1) ; extra == 'testing'
Requires-Dist: openpyxl (==3.0.4) ; extra == 'testing'
Requires-Dist: xlrd (==1.2.0) ; extra == 'testing'
Requires-Dist: tables (==3.6.1) ; extra == 'testing'
Requires-Dist: pyarrow (==0.17.1) ; extra == 'testing'
Requires-Dist: numpy (==1.18.2) ; extra == 'testing'
Requires-Dist: scipy (==1.4.1) ; extra == 'testing'
Requires-Dist: scikit-learn (==0.22.2) ; extra == 'testing'
Requires-Dist: sqlalchemy (==1.3.16) ; extra == 'testing'
Requires-Dist: psycopg2-binary (==2.8.5) ; extra == 'testing'
Requires-Dist: tensorflow (==2.0.1) ; extra == 'testing'
Requires-Dist: catboost (==0.22) ; extra == 'testing'
Requires-Dist: flasgger (==0.9.3) ; extra == 'testing'
Requires-Dist: aiohttp (==3.6.2) ; extra == 'testing'
Requires-Dist: aiohttp-swagger (==1.0.14) ; extra == 'testing'
Requires-Dist: pyyaml (==5.3.1) ; extra == 'testing'
Requires-Dist: boto3 (==1.12.39) ; extra == 'testing'
Requires-Dist: imageio (==2.8.0) ; extra == 'testing'
Requires-Dist: responses (==0.10.12) ; extra == 'testing'
Requires-Dist: psutil (==5.7.0) ; extra == 'testing'
Requires-Dist: testcontainers (==2.6.0) ; extra == 'testing'
Requires-Dist: pytest (==5.2.2) ; extra == 'testing'
Requires-Dist: xgboost (==1.0.2) ; extra == 'testing'
Requires-Dist: lightgbm (==2.3.1) ; extra == 'testing'
Requires-Dist: torch (==1.4.0+cpu) ; (sys_platform != "darwin") and extra == 'testing'
Requires-Dist: torch (==1.4.0) ; (sys_platform == "darwin") and extra == 'testing'
